piblin_jax/__init__.py
piblin_jax/backend/__init__.py
piblin_jax/backend/operations.py
piblin_jax/bayesian/__init__.py
piblin_jax/bayesian/base.py
piblin_jax/bayesian/models/__init__.py
piblin_jax/bayesian/models/arrhenius.py
piblin_jax/bayesian/models/carreau_yasuda.py
piblin_jax/bayesian/models/cross.py
piblin_jax/bayesian/models/power_law.py
piblin_jax/data/__init__.py
piblin_jax/data/metadata.py
piblin_jax/data/roi.py
piblin_jax/data/collections/__init__.py
piblin_jax/data/collections/consistent_measurement_set.py
piblin_jax/data/collections/experiment.py
piblin_jax/data/collections/experiment_set.py
piblin_jax/data/collections/measurement.py
piblin_jax/data/collections/measurement_set.py
piblin_jax/data/collections/tabular_measurement_set.py
piblin_jax/data/collections/tidy_measurement_set.py
piblin_jax/data/datasets/__init__.py
piblin_jax/data/datasets/base.py
piblin_jax/data/datasets/composite.py
piblin_jax/data/datasets/distribution.py
piblin_jax/data/datasets/histogram.py
piblin_jax/data/datasets/one_dimensional.py
piblin_jax/data/datasets/three_dimensional.py
piblin_jax/data/datasets/two_dimensional.py
piblin_jax/data/datasets/zero_dimensional.py
piblin_jax/dataio/__init__.py
piblin_jax/dataio/hierarchy.py
piblin_jax/dataio/readers/__init__.py
piblin_jax/dataio/readers/csv.py
piblin_jax/dataio/readers/txt.py
piblin_jax/dataio/writers/__init__.py
piblin_jax/fitting/__init__.py
piblin_jax/fitting/nlsq.py
piblin_jax/transform/__init__.py
piblin_jax/transform/base.py
piblin_jax/transform/lambda_transform.py
piblin_jax/transform/pipeline.py
piblin_jax/transform/dataset/__init__.py
piblin_jax/transform/dataset/baseline.py
piblin_jax/transform/dataset/calculus.py
piblin_jax/transform/dataset/interpolate.py
piblin_jax/transform/dataset/normalization.py
piblin_jax/transform/dataset/smoothing.py
piblin_jax/transform/measurement/__init__.py
piblin_jax/transform/measurement/filter.py
piblin_jax/transform/region/__init__.py
piblin_jax-0.0.3.dist-info/licenses/LICENSE
piblin_jax-0.0.3.dist-info/METADATA
piblin_jax-0.0.3.dist-info/WHEEL
piblin_jax-0.0.3.dist-info/top_level.txt
piblin_jax-0.0.3.dist-info/RECORD
