Metadata-Version: 2.4
Name: piblin-jax
Version: 0.0.3
Summary: Modern JAX-Powered Framework for Measurement Data Science
Author-email: Wei Chen <wchen@anl.gov>
License: MIT
Project-URL: Homepage, https://github.com/piblin/piblin-jax
Project-URL: Documentation, https://piblin-jax.readthedocs.io
Project-URL: Repository, https://github.com/piblin/piblin-jax
Project-URL: Bug Tracker, https://github.com/piblin/piblin-jax/issues
Keywords: scientific-computing,data-analysis,rheology,jax,bayesian-inference,uncertainty-quantification
Classifier: Development Status :: 3 - Alpha
Classifier: Intended Audience :: Science/Research
Classifier: License :: OSI Approved :: MIT License
Classifier: Operating System :: OS Independent
Classifier: Programming Language :: Python :: 3
Classifier: Programming Language :: Python :: 3.12
Classifier: Programming Language :: Python :: 3.13
Classifier: Programming Language :: Python :: 3.14
Classifier: Topic :: Scientific/Engineering
Classifier: Topic :: Scientific/Engineering :: Chemistry
Classifier: Topic :: Scientific/Engineering :: Physics
Requires-Python: >=3.12
License-File: LICENSE
Requires-Dist: jax<0.9.0,>=0.8.0
Requires-Dist: numpyro>=0.19.0
Requires-Dist: numpy>=2.3.4
Requires-Dist: scipy>=1.16.2
Requires-Dist: matplotlib>=3.10.7
Requires-Dist: pandas>=2.3.3
Provides-Extra: dev
Requires-Dist: pytest>=8.4.2; extra == "dev"
Requires-Dist: pytest-cov>=7.0.0; extra == "dev"
Requires-Dist: pytest-mpl>=0.17.0; extra == "dev"
Requires-Dist: pytest-benchmark>=5.1.0; extra == "dev"
Requires-Dist: hypothesis>=6.142.0; extra == "dev"
Requires-Dist: mypy>=1.18.2; extra == "dev"
Requires-Dist: ruff>=0.14.1; extra == "dev"
Requires-Dist: pre-commit>=4.3.0; extra == "dev"
Requires-Dist: build>=1.3.0; extra == "dev"
Requires-Dist: interrogate>=1.7.0; extra == "dev"
Provides-Extra: test
Requires-Dist: pytest>=8.4.2; extra == "test"
Requires-Dist: pytest-cov>=7.0.0; extra == "test"
Requires-Dist: pytest-mpl>=0.17.0; extra == "test"
Requires-Dist: pytest-benchmark>=5.1.0; extra == "test"
Requires-Dist: hypothesis>=6.142.0; extra == "test"
Provides-Extra: docs
Requires-Dist: sphinx>=8.2.3; extra == "docs"
Requires-Dist: sphinx-rtd-theme>=3.0.2; extra == "docs"
Requires-Dist: numpydoc>=1.9.0; extra == "docs"
Provides-Extra: security
Requires-Dist: pip-audit>=2.9.0; extra == "security"
Requires-Dist: pip-licenses>=5.5.0; extra == "security"
Requires-Dist: cyclonedx-bom>=7.1.0; extra == "security"
Requires-Dist: bandit[toml]>=1.8.6; extra == "security"
Provides-Extra: all
Requires-Dist: piblin-jax[dev,docs,test]; extra == "all"
Dynamic: license-file
